{
  "system_metrics": [
    {
      "timestamp": "2025-10-02T06:27:07.074821",
      "cpu_percent": 4.7,
      "memory_percent": 64.2,
      "memory_used_mb": 10281.34765625,
      "memory_available_mb": 5735.12890625,
      "disk_percent": 92.44752888154454,
      "disk_used_gb": 219.23876953125,
      "disk_free_gb": 17.910640716552734,
      "active_connections": 290
    },
    {
      "timestamp": "2025-10-02T06:28:29.020504",
      "cpu_percent": 5.1,
      "memory_percent": 64.1,
      "memory_used_mb": 10272.0703125,
      "memory_available_mb": 5744.40625,
      "disk_percent": 92.44754335861002,
      "disk_used_gb": 219.2388038635254,
      "disk_free_gb": 17.910606384277344,
      "active_connections": 298
    },
    {
      "timestamp": "2025-10-02T06:29:30.055577",
      "cpu_percent": 1.8,
      "memory_percent": 64.1,
      "memory_used_mb": 10262.703125,
      "memory_available_mb": 5753.7734375,
      "disk_percent": 92.44758035555512,
      "disk_used_gb": 219.2388916015625,
      "disk_free_gb": 17.910518646240234,
      "active_connections": 288
    },
    {
      "timestamp": "2025-10-02T06:30:31.063029",
      "cpu_percent": 1.0,
      "memory_percent": 64.2,
      "memory_used_mb": 10289.03515625,
      "memory_available_mb": 5727.44140625,
      "disk_percent": 92.4478602454876,
      "disk_used_gb": 219.23955535888672,
      "disk_free_gb": 17.909854888916016,
      "active_connections": 291
    },
    {
      "timestamp": "2025-10-02T06:31:32.071971",
      "cpu_percent": 1.3,
      "memory_percent": 64.3,
      "memory_used_mb": 10292.28125,
      "memory_available_mb": 5724.1953125,
      "disk_percent": 92.44800984183082,
      "disk_used_gb": 219.23991012573242,
      "disk_free_gb": 17.909500122070312,
      "active_connections": 291
    },
    {
      "timestamp": "2025-10-02T06:32:33.084619",
      "cpu_percent": 1.6,
      "memory_percent": 64.4,
      "memory_used_mb": 10312.99609375,
      "memory_available_mb": 5703.48046875,
      "disk_percent": 92.44804362165026,
      "disk_used_gb": 219.239990234375,
      "disk_free_gb": 17.909420013427734,
      "active_connections": 287
    },
    {
      "timestamp": "2025-10-02T06:33:38.195687",
      "cpu_percent": 4.7,
      "memory_percent": 65.0,
      "memory_used_mb": 10404.2265625,
      "memory_available_mb": 5612.25,
      "disk_percent": 92.44814978679706,
      "disk_used_gb": 219.24024200439453,
      "disk_free_gb": 17.909168243408203,
      "active_connections": 306
    },
    {
      "timestamp": "2025-10-02T06:34:39.224815",
      "cpu_percent": 1.3,
      "memory_percent": 65.2,
      "memory_used_mb": 10444.89453125,
      "memory_available_mb": 5571.58203125,
      "disk_percent": 92.44827203757217,
      "disk_used_gb": 219.24053192138672,
      "disk_free_gb": 17.908878326416016,
      "active_connections": 303
    },
    {
      "timestamp": "2025-10-02T06:35:40.250030",
      "cpu_percent": 1.6,
      "memory_percent": 65.3,
      "memory_used_mb": 10458.5625,
      "memory_available_mb": 5557.9140625,
      "disk_percent": 92.44828651463764,
      "disk_used_gb": 219.2405662536621,
      "disk_free_gb": 17.908843994140625,
      "active_connections": 284
    },
    {
      "timestamp": "2025-10-02T06:36:41.249375",
      "cpu_percent": 5.2,
      "memory_percent": 65.6,
      "memory_used_mb": 10505.30859375,
      "memory_available_mb": 5511.16796875,
      "disk_percent": 92.44829938314028,
      "disk_used_gb": 219.24059677124023,
      "disk_free_gb": 17.9088134765625,
      "active_connections": 283
    },
    {
      "timestamp": "2025-10-02T06:37:42.268934",
      "cpu_percent": 1.7,
      "memory_percent": 64.7,
      "memory_used_mb": 10363.75,
      "memory_available_mb": 5652.7265625,
      "disk_percent": 92.44831546876858,
      "disk_used_gb": 219.2406349182129,
      "disk_free_gb": 17.908775329589844,
      "active_connections": 296
    },
    {
      "timestamp": "2025-10-02T06:38:47.409692",
      "cpu_percent": 1.4,
      "memory_percent": 65.1,
      "memory_used_mb": 10428.7265625,
      "memory_available_mb": 5587.75,
      "disk_percent": 92.44866774402844,
      "disk_used_gb": 219.24147033691406,
      "disk_free_gb": 17.907939910888672,
      "active_connections": 312
    },
    {
      "timestamp": "2025-10-02T06:39:48.429236",
      "cpu_percent": 1.6,
      "memory_percent": 65.3,
      "memory_used_mb": 10464.2421875,
      "memory_available_mb": 5552.234375,
      "disk_percent": 92.44875460642128,
      "disk_used_gb": 219.2416763305664,
      "disk_free_gb": 17.907733917236328,
      "active_connections": 288
    },
    {
      "timestamp": "2025-10-02T06:40:49.444046",
      "cpu_percent": 1.2,
      "memory_percent": 65.2,
      "memory_used_mb": 10448.60546875,
      "memory_available_mb": 5567.87109375,
      "disk_percent": 92.44877390917523,
      "disk_used_gb": 219.2417221069336,
      "disk_free_gb": 17.90768814086914,
      "active_connections": 285
    },
    {
      "timestamp": "2025-10-02T06:41:50.469886",
      "cpu_percent": 4.2,
      "memory_percent": 65.4,
      "memory_used_mb": 10469.41015625,
      "memory_available_mb": 5547.06640625,
      "disk_percent": 92.44766882651079,
      "disk_used_gb": 219.2391014099121,
      "disk_free_gb": 17.910308837890625,
      "active_connections": 286
    },
    {
      "timestamp": "2025-10-02T06:42:51.492466",
      "cpu_percent": 1.2,
      "memory_percent": 65.6,
      "memory_used_mb": 10504.18359375,
      "memory_available_mb": 5512.29296875,
      "disk_percent": 92.44768330357627,
      "disk_used_gb": 219.2391357421875,
      "disk_free_gb": 17.910274505615234,
      "active_connections": 290
    },
    {
      "timestamp": "2025-10-02T06:43:56.787403",
      "cpu_percent": 0.4,
      "memory_percent": 65.5,
      "memory_used_mb": 10497.49609375,
      "memory_available_mb": 5518.98046875,
      "disk_percent": 92.44773960327532,
      "disk_used_gb": 219.2392692565918,
      "disk_free_gb": 17.910140991210938,
      "active_connections": 296
    },
    {
      "timestamp": "2025-10-02T06:44:57.790307",
      "cpu_percent": 1.6,
      "memory_percent": 65.4,
      "memory_used_mb": 10476.1953125,
      "memory_available_mb": 5540.28125,
      "disk_percent": 92.44777981734609,
      "disk_used_gb": 219.23936462402344,
      "disk_free_gb": 17.910045623779297,
      "active_connections": 287
    },
    {
      "timestamp": "2025-10-02T06:45:58.789537",
      "cpu_percent": 2.1,
      "memory_percent": 65.4,
      "memory_used_mb": 10482.23046875,
      "memory_available_mb": 5534.24609375,
      "disk_percent": 92.44779268584873,
      "disk_used_gb": 219.23939514160156,
      "disk_free_gb": 17.910015106201172,
      "active_connections": 293
    },
    {
      "timestamp": "2025-10-02T06:46:59.810069",
      "cpu_percent": 1.8,
      "memory_percent": 65.5,
      "memory_used_mb": 10485.02734375,
      "memory_available_mb": 5531.44921875,
      "disk_percent": 92.44780072866288,
      "disk_used_gb": 219.2394142150879,
      "disk_free_gb": 17.909996032714844,
      "active_connections": 298
    },
    {
      "timestamp": "2025-10-02T06:48:00.817648",
      "cpu_percent": 3.9,
      "memory_percent": 65.9,
      "memory_used_mb": 10559.87890625,
      "memory_available_mb": 5456.59765625,
      "disk_percent": 92.44802753602195,
      "disk_used_gb": 219.23995208740234,
      "disk_free_gb": 17.90945816040039,
      "active_connections": 347
    },
    {
      "timestamp": "2025-10-02T06:49:06.035219",
      "cpu_percent": 4.7,
      "memory_percent": 65.6,
      "memory_used_mb": 10506.17578125,
      "memory_available_mb": 5510.30078125,
      "disk_percent": 92.44867578684259,
      "disk_used_gb": 219.2414894104004,
      "disk_free_gb": 17.907920837402344,
      "active_connections": 331
    },
    {
      "timestamp": "2025-10-02T06:50:07.068035",
      "cpu_percent": 2.6,
      "memory_percent": 66.0,
      "memory_used_mb": 10564.27734375,
      "memory_available_mb": 5452.19921875,
      "disk_percent": 92.44880286330618,
      "disk_used_gb": 219.24179077148438,
      "disk_free_gb": 17.90761947631836,
      "active_connections": 352
    },
    {
      "timestamp": "2025-10-02T06:51:08.087665",
      "cpu_percent": 3.0,
      "memory_percent": 67.6,
      "memory_used_mb": 10823.50390625,
      "memory_available_mb": 5192.97265625,
      "disk_percent": 92.44879803761769,
      "disk_used_gb": 219.24177932739258,
      "disk_free_gb": 17.907630920410156,
      "active_connections": 328
    },
    {
      "timestamp": "2025-10-02T06:52:09.100869",
      "cpu_percent": 4.5,
      "memory_percent": 67.2,
      "memory_used_mb": 10766.421875,
      "memory_available_mb": 5250.0546875,
      "disk_percent": 92.44896693671487,
      "disk_used_gb": 219.24217987060547,
      "disk_free_gb": 17.907230377197266,
      "active_connections": 321
    },
    {
      "timestamp": "2025-10-02T06:53:10.118537",
      "cpu_percent": 6.2,
      "memory_percent": 67.2,
      "memory_used_mb": 10756.9140625,
      "memory_available_mb": 5259.5625,
      "disk_percent": 92.44853584187635,
      "disk_used_gb": 219.24115753173828,
      "disk_free_gb": 17.908252716064453,
      "active_connections": 321
    },
    {
      "timestamp": "2025-10-02T06:54:32.081336",
      "cpu_percent": 2.1,
      "memory_percent": 67.3,
      "memory_used_mb": 10779.49609375,
      "memory_available_mb": 5236.98046875,
      "disk_percent": 92.44861466145503,
      "disk_used_gb": 219.2413444519043,
      "disk_free_gb": 17.908065795898438,
      "active_connections": 327
    },
    {
      "timestamp": "2025-10-02T06:55:33.082975",
      "cpu_percent": 3.4,
      "memory_percent": 67.3,
      "memory_used_mb": 10774.71875,
      "memory_available_mb": 5241.7578125,
      "disk_percent": 92.44869508959654,
      "disk_used_gb": 219.24153518676758,
      "disk_free_gb": 17.907875061035156,
      "active_connections": 324
    },
    {
      "timestamp": "2025-10-02T06:56:34.082349",
      "cpu_percent": 3.6,
      "memory_percent": 67.4,
      "memory_used_mb": 10794.40625,
      "memory_available_mb": 5222.0703125,
      "disk_percent": 92.4487610406726,
      "disk_used_gb": 219.24169158935547,
      "disk_free_gb": 17.907718658447266,
      "active_connections": 331
    }
  ],
  "api_metrics": [],
  "error_counts": {
    "404": 602,
    "401": 249,
    "422": 5
  },
  "time_range": {
    "start": "2025-10-02T06:27:04.094408",
    "end": "2025-10-02T06:57:04.094408"
  }
}