{
  "system_metrics": [
    {
      "timestamp": "2025-10-01T16:50:47.025209",
      "cpu_percent": 1.6,
      "memory_percent": 84.9,
      "memory_used_mb": 13600.33203125,
      "memory_available_mb": 2416.14453125,
      "disk_percent": 92.72162798783509,
      "disk_used_gb": 219.8887939453125,
      "disk_free_gb": 17.260616302490234,
      "active_connections": 287
    },
    {
      "timestamp": "2025-10-01T16:51:49.601160",
      "cpu_percent": 1.0,
      "memory_percent": 85.4,
      "memory_used_mb": 13684.859375,
      "memory_available_mb": 2331.6171875,
      "disk_percent": 92.72166176765452,
      "disk_used_gb": 219.88887405395508,
      "disk_free_gb": 17.260536193847656,
      "active_connections": 280
    },
    {
      "timestamp": "2025-10-01T16:52:50.622834",
      "cpu_percent": 1.2,
      "memory_percent": 84.7,
      "memory_used_mb": 13572.58984375,
      "memory_available_mb": 2443.88671875,
      "disk_percent": 92.72163763921206,
      "disk_used_gb": 219.8888168334961,
      "disk_free_gb": 17.26059341430664,
      "active_connections": 276
    },
    {
      "timestamp": "2025-10-01T16:53:51.650103",
      "cpu_percent": 1.7,
      "memory_percent": 84.8,
      "memory_used_mb": 13587.6875,
      "memory_available_mb": 2428.7890625,
      "disk_percent": 92.72139635478752,
      "disk_used_gb": 219.88824462890625,
      "disk_free_gb": 17.261165618896484,
      "active_connections": 283
    },
    {
      "timestamp": "2025-10-01T16:54:52.665837",
      "cpu_percent": 0.4,
      "memory_percent": 84.8,
      "memory_used_mb": 13586.01953125,
      "memory_available_mb": 2430.45703125,
      "disk_percent": 92.72148482574319,
      "disk_used_gb": 219.88845443725586,
      "disk_free_gb": 17.260955810546875,
      "active_connections": 275
    },
    {
      "timestamp": "2025-10-01T16:55:53.695294",
      "cpu_percent": 2.6,
      "memory_percent": 84.9,
      "memory_used_mb": 13594.5625,
      "memory_available_mb": 2421.9140625,
      "disk_percent": 92.72151860556261,
      "disk_used_gb": 219.88853454589844,
      "disk_free_gb": 17.260875701904297,
      "active_connections": 286
    },
    {
      "timestamp": "2025-10-01T16:56:56.257982",
      "cpu_percent": 4.0,
      "memory_percent": 85.2,
      "memory_used_mb": 13638.3984375,
      "memory_available_mb": 2378.078125,
      "disk_percent": 92.72156686244753,
      "disk_used_gb": 219.8886489868164,
      "disk_free_gb": 17.260761260986328,
      "active_connections": 281
    },
    {
      "timestamp": "2025-10-01T16:57:57.264488",
      "cpu_percent": 5.3,
      "memory_percent": 85.3,
      "memory_used_mb": 13655.19921875,
      "memory_available_mb": 2361.27734375,
      "disk_percent": 92.72190466064191,
      "disk_used_gb": 219.8894500732422,
      "disk_free_gb": 17.259960174560547,
      "active_connections": 286
    },
    {
      "timestamp": "2025-10-01T16:58:58.301310",
      "cpu_percent": 2.5,
      "memory_percent": 85.3,
      "memory_used_mb": 13657.125,
      "memory_available_mb": 2359.3515625,
      "disk_percent": 92.72192718052152,
      "disk_used_gb": 219.8895034790039,
      "disk_free_gb": 17.259906768798828,
      "active_connections": 282
    },
    {
      "timestamp": "2025-10-01T16:59:59.315569",
      "cpu_percent": 4.3,
      "memory_percent": 85.4,
      "memory_used_mb": 13684.77734375,
      "memory_available_mb": 2331.69921875,
      "disk_percent": 92.72268159648895,
      "disk_used_gb": 219.89129257202148,
      "disk_free_gb": 17.25811767578125,
      "active_connections": 283
    },
    {
      "timestamp": "2025-10-01T17:01:00.331500",
      "cpu_percent": 4.3,
      "memory_percent": 86.1,
      "memory_used_mb": 13790.03125,
      "memory_available_mb": 2226.4453125,
      "disk_percent": 92.72314325402127,
      "disk_used_gb": 219.89238739013672,
      "disk_free_gb": 17.257022857666016,
      "active_connections": 288
    },
    {
      "timestamp": "2025-10-01T17:02:02.874652",
      "cpu_percent": 2.2,
      "memory_percent": 84.5,
      "memory_used_mb": 13528.328125,
      "memory_available_mb": 2488.1484375,
      "disk_percent": 92.7236435170615,
      "disk_used_gb": 219.89357376098633,
      "disk_free_gb": 17.255836486816406,
      "active_connections": 293
    },
    {
      "timestamp": "2025-10-01T17:03:03.877373",
      "cpu_percent": 2.1,
      "memory_percent": 85.0,
      "memory_used_mb": 13611.703125,
      "memory_available_mb": 2404.7734375,
      "disk_percent": 92.72372555376585,
      "disk_used_gb": 219.89376831054688,
      "disk_free_gb": 17.25564193725586,
      "active_connections": 276
    },
    {
      "timestamp": "2025-10-01T17:04:04.877264",
      "cpu_percent": 2.2,
      "memory_percent": 85.0,
      "memory_used_mb": 13608.046875,
      "memory_available_mb": 2408.4296875,
      "disk_percent": 92.72383332747548,
      "disk_used_gb": 219.89402389526367,
      "disk_free_gb": 17.255386352539062,
      "active_connections": 280
    },
    {
      "timestamp": "2025-10-01T17:05:05.897291",
      "cpu_percent": 4.2,
      "memory_percent": 85.0,
      "memory_used_mb": 13608.68359375,
      "memory_available_mb": 2407.79296875,
      "disk_percent": 92.72439149877762,
      "disk_used_gb": 219.89534759521484,
      "disk_free_gb": 17.25406265258789,
      "active_connections": 280
    },
    {
      "timestamp": "2025-10-01T17:06:06.912160",
      "cpu_percent": 1.3,
      "memory_percent": 85.0,
      "memory_used_mb": 13614.796875,
      "memory_available_mb": 2401.6796875,
      "disk_percent": 92.72450088105008,
      "disk_used_gb": 219.8956069946289,
      "disk_free_gb": 17.253803253173828,
      "active_connections": 281
    },
    {
      "timestamp": "2025-10-01T17:07:09.482981",
      "cpu_percent": 3.0,
      "memory_percent": 85.2,
      "memory_used_mb": 13639.87890625,
      "memory_available_mb": 2376.59765625,
      "disk_percent": 92.72488211044086,
      "disk_used_gb": 219.89651107788086,
      "disk_free_gb": 17.252899169921875,
      "active_connections": 305
    },
    {
      "timestamp": "2025-10-01T17:08:10.506704",
      "cpu_percent": 5.5,
      "memory_percent": 85.2,
      "memory_used_mb": 13640.58203125,
      "memory_available_mb": 2375.89453125,
      "disk_percent": 92.72502527253278,
      "disk_used_gb": 219.8968505859375,
      "disk_free_gb": 17.252559661865234,
      "active_connections": 305
    },
    {
      "timestamp": "2025-10-01T17:09:11.513954",
      "cpu_percent": 1.4,
      "memory_percent": 85.4,
      "memory_used_mb": 13685.0390625,
      "memory_available_mb": 2331.4375,
      "disk_percent": 92.725079963669,
      "disk_used_gb": 219.89698028564453,
      "disk_free_gb": 17.252429962158203,
      "active_connections": 284
    },
    {
      "timestamp": "2025-10-01T17:10:12.509007",
      "cpu_percent": 2.5,
      "memory_percent": 85.7,
      "memory_used_mb": 13721.3203125,
      "memory_available_mb": 2295.15625,
      "disk_percent": 92.72520060588127,
      "disk_used_gb": 219.89726638793945,
      "disk_free_gb": 17.25214385986328,
      "active_connections": 286
    },
    {
      "timestamp": "2025-10-01T17:11:13.525566",
      "cpu_percent": 3.5,
      "memory_percent": 86.3,
      "memory_used_mb": 13818.0390625,
      "memory_available_mb": 2198.4375,
      "disk_percent": 92.72521669150959,
      "disk_used_gb": 219.8973045349121,
      "disk_free_gb": 17.252105712890625,
      "active_connections": 285
    },
    {
      "timestamp": "2025-10-01T17:12:16.124215",
      "cpu_percent": 0.9,
      "memory_percent": 85.5,
      "memory_used_mb": 13700.609375,
      "memory_available_mb": 2315.8671875,
      "disk_percent": 92.72524081995203,
      "disk_used_gb": 219.8973617553711,
      "disk_free_gb": 17.25204849243164,
      "active_connections": 287
    },
    {
      "timestamp": "2025-10-01T17:13:17.150204",
      "cpu_percent": 1.3,
      "memory_percent": 85.7,
      "memory_used_mb": 13731.29296875,
      "memory_available_mb": 2285.18359375,
      "disk_percent": 92.72534376797317,
      "disk_used_gb": 219.8976058959961,
      "disk_free_gb": 17.25180435180664,
      "active_connections": 285
    },
    {
      "timestamp": "2025-10-01T17:14:18.173569",
      "cpu_percent": 3.8,
      "memory_percent": 85.9,
      "memory_used_mb": 13758.09375,
      "memory_available_mb": 2258.3828125,
      "disk_percent": 92.72524886276618,
      "disk_used_gb": 219.89738082885742,
      "disk_free_gb": 17.252029418945312,
      "active_connections": 272
    },
    {
      "timestamp": "2025-10-01T17:15:19.207861",
      "cpu_percent": 2.5,
      "memory_percent": 86.2,
      "memory_used_mb": 13800.2578125,
      "memory_available_mb": 2216.21875,
      "disk_percent": 92.72533894228468,
      "disk_used_gb": 219.8975944519043,
      "disk_free_gb": 17.251815795898438,
      "active_connections": 280
    },
    {
      "timestamp": "2025-10-01T17:16:20.216693",
      "cpu_percent": 4.8,
      "memory_percent": 86.1,
      "memory_used_mb": 13789.51171875,
      "memory_available_mb": 2226.96484375,
      "disk_percent": 92.76940552102194,
      "disk_used_gb": 220.0020980834961,
      "disk_free_gb": 17.14731216430664,
      "active_connections": 274
    },
    {
      "timestamp": "2025-10-01T17:17:22.816382",
      "cpu_percent": 1.8,
      "memory_percent": 85.3,
      "memory_used_mb": 13668.43359375,
      "memory_available_mb": 2348.04296875,
      "disk_percent": 92.76947951491215,
      "disk_used_gb": 220.0022735595703,
      "disk_free_gb": 17.147136688232422,
      "active_connections": 287
    },
    {
      "timestamp": "2025-10-01T17:18:23.846732",
      "cpu_percent": 3.1,
      "memory_percent": 84.5,
      "memory_used_mb": 13533.78515625,
      "memory_available_mb": 2482.69140625,
      "disk_percent": 92.76939426108214,
      "disk_used_gb": 220.00207138061523,
      "disk_free_gb": 17.1473388671875,
      "active_connections": 290
    },
    {
      "timestamp": "2025-10-01T17:19:24.861712",
      "cpu_percent": 10.3,
      "memory_percent": 84.9,
      "memory_used_mb": 13597.43359375,
      "memory_available_mb": 2419.04296875,
      "disk_percent": 92.76948916628912,
      "disk_used_gb": 220.0022964477539,
      "disk_free_gb": 17.147113800048828,
      "active_connections": 288
    },
    {
      "timestamp": "2025-10-01T17:20:25.889022",
      "cpu_percent": 3.8,
      "memory_percent": 85.6,
      "memory_used_mb": 13711.71484375,
      "memory_available_mb": 2304.76171875,
      "disk_percent": 92.77251004728451,
      "disk_used_gb": 220.00946044921875,
      "disk_free_gb": 17.139949798583984,
      "active_connections": 280
    }
  ],
  "api_metrics": [],
  "error_counts": {},
  "time_range": {
    "start": "2025-10-01T16:50:25.891640",
    "end": "2025-10-01T17:20:25.892661"
  }
}