{
  "system_metrics": [
    {
      "timestamp": "2025-10-01T13:03:46.483556",
      "cpu_percent": 13.9,
      "memory_percent": 94.0,
      "memory_used_mb": 15052.07421875,
      "memory_available_mb": 964.40234375,
      "disk_percent": 92.20777902593316,
      "disk_used_gb": 218.67020416259766,
      "disk_free_gb": 18.479206085205078,
      "active_connections": 322
    },
    {
      "timestamp": "2025-10-01T13:04:49.154654",
      "cpu_percent": 11.2,
      "memory_percent": 91.8,
      "memory_used_mb": 14697.0,
      "memory_available_mb": 1319.4765625,
      "disk_percent": 92.20772433479694,
      "disk_used_gb": 218.67007446289062,
      "disk_free_gb": 18.47933578491211,
      "active_connections": 368
    },
    {
      "timestamp": "2025-10-01T13:05:50.190118",
      "cpu_percent": 31.5,
      "memory_percent": 92.1,
      "memory_used_mb": 14743.57421875,
      "memory_available_mb": 1272.90234375,
      "disk_percent": 92.20777580880751,
      "disk_used_gb": 218.67019653320312,
      "disk_free_gb": 18.47921371459961,
      "active_connections": 317
    },
    {
      "timestamp": "2025-10-01T13:06:51.233693",
      "cpu_percent": 7.0,
      "memory_percent": 91.9,
      "memory_used_mb": 14726.6171875,
      "memory_available_mb": 1289.859375,
      "disk_percent": 92.20791575377375,
      "disk_used_gb": 218.67052841186523,
      "disk_free_gb": 18.4788818359375,
      "active_connections": 315
    },
    {
      "timestamp": "2025-10-01T13:07:52.249789",
      "cpu_percent": 10.7,
      "memory_percent": 93.3,
      "memory_used_mb": 14946.89453125,
      "memory_available_mb": 1069.58203125,
      "disk_percent": 92.20875703213402,
      "disk_used_gb": 218.67252349853516,
      "disk_free_gb": 18.476886749267578,
      "active_connections": 346
    },
    {
      "timestamp": "2025-10-01T13:08:53.259855",
      "cpu_percent": 10.0,
      "memory_percent": 93.2,
      "memory_used_mb": 14927.7109375,
      "memory_available_mb": 1088.765625,
      "disk_percent": 92.21083207818516,
      "disk_used_gb": 218.6774444580078,
      "disk_free_gb": 18.471965789794922,
      "active_connections": 322
    },
    {
      "timestamp": "2025-10-01T13:09:55.845675",
      "cpu_percent": 18.7,
      "memory_percent": 94.7,
      "memory_used_mb": 15172.64453125,
      "memory_available_mb": 843.83203125,
      "disk_percent": 92.21088516075856,
      "disk_used_gb": 218.67757034301758,
      "disk_free_gb": 18.471839904785156,
      "active_connections": 329
    },
    {
      "timestamp": "2025-10-01T13:10:56.892513",
      "cpu_percent": 23.0,
      "memory_percent": 95.5,
      "memory_used_mb": 15300.27734375,
      "memory_available_mb": 716.19921875,
      "disk_percent": 92.21104762560442,
      "disk_used_gb": 218.6779556274414,
      "disk_free_gb": 18.471454620361328,
      "active_connections": 314
    },
    {
      "timestamp": "2025-10-01T13:11:57.939766",
      "cpu_percent": 20.1,
      "memory_percent": 93.6,
      "memory_used_mb": 14989.3125,
      "memory_available_mb": 1027.1640625,
      "disk_percent": 92.21052323412174,
      "disk_used_gb": 218.6767120361328,
      "disk_free_gb": 18.472698211669922,
      "active_connections": 321
    },
    {
      "timestamp": "2025-10-01T13:12:58.993533",
      "cpu_percent": 19.8,
      "memory_percent": 94.7,
      "memory_used_mb": 15165.74609375,
      "memory_available_mb": 850.73046875,
      "disk_percent": 92.21218487952548,
      "disk_used_gb": 218.6806526184082,
      "disk_free_gb": 18.46875762939453,
      "active_connections": 346
    },
    {
      "timestamp": "2025-10-01T13:14:00.024580",
      "cpu_percent": 17.3,
      "memory_percent": 93.2,
      "memory_used_mb": 14922.50390625,
      "memory_available_mb": 1093.97265625,
      "disk_percent": 92.21028999251133,
      "disk_used_gb": 218.6761589050293,
      "disk_free_gb": 18.473251342773438,
      "active_connections": 344
    },
    {
      "timestamp": "2025-10-01T13:15:02.608531",
      "cpu_percent": 9.9,
      "memory_percent": 91.6,
      "memory_used_mb": 14674.00390625,
      "memory_available_mb": 1342.47265625,
      "disk_percent": 92.21040902616078,
      "disk_used_gb": 218.67644119262695,
      "disk_free_gb": 18.47296905517578,
      "active_connections": 321
    },
    {
      "timestamp": "2025-10-01T13:16:03.644838",
      "cpu_percent": 17.5,
      "memory_percent": 92.0,
      "memory_used_mb": 14737.16015625,
      "memory_available_mb": 1279.31640625,
      "disk_percent": 92.21052484268458,
      "disk_used_gb": 218.67671585083008,
      "disk_free_gb": 18.472694396972656,
      "active_connections": 307
    },
    {
      "timestamp": "2025-10-01T13:17:04.673858",
      "cpu_percent": 15.5,
      "memory_percent": 93.0,
      "memory_used_mb": 14899.83203125,
      "memory_available_mb": 1116.64453125,
      "disk_percent": 92.21069535034458,
      "disk_used_gb": 218.67712020874023,
      "disk_free_gb": 18.4722900390625,
      "active_connections": 297
    },
    {
      "timestamp": "2025-10-01T13:18:05.685773",
      "cpu_percent": 14.1,
      "memory_percent": 92.8,
      "memory_used_mb": 14858.8359375,
      "memory_available_mb": 1157.640625,
      "disk_percent": 92.21074682435516,
      "disk_used_gb": 218.67724227905273,
      "disk_free_gb": 18.47216796875,
      "active_connections": 292
    },
    {
      "timestamp": "2025-10-01T13:19:06.693218",
      "cpu_percent": 13.4,
      "memory_percent": 92.4,
      "memory_used_mb": 14801.6484375,
      "memory_available_mb": 1214.828125,
      "disk_percent": 92.21084172956215,
      "disk_used_gb": 218.6774673461914,
      "disk_free_gb": 18.471942901611328,
      "active_connections": 298
    },
    {
      "timestamp": "2025-10-01T13:20:09.311113",
      "cpu_percent": 13.0,
      "memory_percent": 92.2,
      "memory_used_mb": 14764.86328125,
      "memory_available_mb": 1251.61328125,
      "disk_percent": 92.21114574793707,
      "disk_used_gb": 218.6781883239746,
      "disk_free_gb": 18.471221923828125,
      "active_connections": 297
    },
    {
      "timestamp": "2025-10-01T13:21:10.317258",
      "cpu_percent": 13.4,
      "memory_percent": 92.5,
      "memory_used_mb": 14818.42578125,
      "memory_available_mb": 1198.05078125,
      "disk_percent": 92.21122778464142,
      "disk_used_gb": 218.67838287353516,
      "disk_free_gb": 18.471027374267578,
      "active_connections": 322
    },
    {
      "timestamp": "2025-10-01T13:22:11.346603",
      "cpu_percent": 12.6,
      "memory_percent": 94.0,
      "memory_used_mb": 15049.50390625,
      "memory_available_mb": 966.97265625,
      "disk_percent": 92.21180525869752,
      "disk_used_gb": 218.67975234985352,
      "disk_free_gb": 18.46965789794922,
      "active_connections": 317
    },
    {
      "timestamp": "2025-10-01T13:23:12.358665",
      "cpu_percent": 17.3,
      "memory_percent": 93.6,
      "memory_used_mb": 14993.3203125,
      "memory_available_mb": 1023.15625,
      "disk_percent": 92.21199185198584,
      "disk_used_gb": 218.68019485473633,
      "disk_free_gb": 18.469215393066406,
      "active_connections": 282
    },
    {
      "timestamp": "2025-10-01T13:24:13.386711",
      "cpu_percent": 34.3,
      "memory_percent": 93.8,
      "memory_used_mb": 15022.19140625,
      "memory_available_mb": 994.28515625,
      "disk_percent": 92.21207871437868,
      "disk_used_gb": 218.68040084838867,
      "disk_free_gb": 18.469009399414062,
      "active_connections": 307
    },
    {
      "timestamp": "2025-10-01T13:25:16.013216",
      "cpu_percent": 10.8,
      "memory_percent": 95.4,
      "memory_used_mb": 15281.6875,
      "memory_available_mb": 734.7890625,
      "disk_percent": 92.21245511808098,
      "disk_used_gb": 218.68129348754883,
      "disk_free_gb": 18.468116760253906,
      "active_connections": 340
    },
    {
      "timestamp": "2025-10-01T13:26:17.057970",
      "cpu_percent": 15.8,
      "memory_percent": 70.7,
      "memory_used_mb": 11317.453125,
      "memory_available_mb": 4699.0234375,
      "disk_percent": 92.21326905087314,
      "disk_used_gb": 218.68322372436523,
      "disk_free_gb": 18.4661865234375,
      "active_connections": 334
    },
    {
      "timestamp": "2025-10-01T13:27:18.102920",
      "cpu_percent": 39.9,
      "memory_percent": 61.5,
      "memory_used_mb": 9846.7265625,
      "memory_available_mb": 6169.75,
      "disk_percent": 92.21479879412479,
      "disk_used_gb": 218.68685150146484,
      "disk_free_gb": 18.46255874633789,
      "active_connections": 355
    },
    {
      "timestamp": "2025-10-01T13:28:19.143059",
      "cpu_percent": 16.4,
      "memory_percent": 62.5,
      "memory_used_mb": 10007.5625,
      "memory_available_mb": 6008.9140625,
      "disk_percent": 92.21532801129597,
      "disk_used_gb": 218.68810653686523,
      "disk_free_gb": 18.4613037109375,
      "active_connections": 327
    },
    {
      "timestamp": "2025-10-01T13:29:20.163342",
      "cpu_percent": 16.0,
      "memory_percent": 65.4,
      "memory_used_mb": 10482.35546875,
      "memory_available_mb": 5534.12109375,
      "disk_percent": 92.2170105680165,
      "disk_used_gb": 218.69209671020508,
      "disk_free_gb": 18.457313537597656,
      "active_connections": 328
    },
    {
      "timestamp": "2025-10-01T13:30:22.780184",
      "cpu_percent": 10.7,
      "memory_percent": 66.8,
      "memory_used_mb": 10698.00390625,
      "memory_available_mb": 5318.47265625,
      "disk_percent": 92.21863521647515,
      "disk_used_gb": 218.69594955444336,
      "disk_free_gb": 18.453460693359375,
      "active_connections": 353
    },
    {
      "timestamp": "2025-10-01T13:31:23.802967",
      "cpu_percent": 9.6,
      "memory_percent": 67.7,
      "memory_used_mb": 10841.953125,
      "memory_available_mb": 5174.5234375,
      "disk_percent": 92.2192947272356,
      "disk_used_gb": 218.69751358032227,
      "disk_free_gb": 18.45189666748047,
      "active_connections": 396
    },
    {
      "timestamp": "2025-10-01T13:32:24.830741",
      "cpu_percent": 13.2,
      "memory_percent": 68.9,
      "memory_used_mb": 11027.6796875,
      "memory_available_mb": 4988.796875,
      "disk_percent": 92.21976925327054,
      "disk_used_gb": 218.69863891601562,
      "disk_free_gb": 18.45077133178711,
      "active_connections": 375
    },
    {
      "timestamp": "2025-10-01T13:33:25.862262",
      "cpu_percent": 24.8,
      "memory_percent": 72.0,
      "memory_used_mb": 11533.38671875,
      "memory_available_mb": 4483.08984375,
      "disk_percent": 92.22009900865076,
      "disk_used_gb": 218.69942092895508,
      "disk_free_gb": 18.449989318847656,
      "active_connections": 300
    }
  ],
  "api_metrics": [],
  "error_counts": {},
  "time_range": {
    "start": "2025-10-01T13:03:25.868747",
    "end": "2025-10-01T13:33:25.869745"
  }
}